gmsg/__init__.py
gmsg/api_key.py
gmsg/gmsg.py
gmsg-0.1.7.dist-info/LICENSE
gmsg-0.1.7.dist-info/METADATA
gmsg-0.1.7.dist-info/WHEEL
gmsg-0.1.7.dist-info/entry_points.txt
gmsg-0.1.7.dist-info/RECORD
