Metadata-Version: 2.3
Name: gmsg
Version: 0.1.7
Summary: Generates git commit messages for you using AI.
License: MIT
Keywords: git,commit,ai
Author: Shiyan Shirani
Author-email: shiyan99s@gmail.com
Requires-Python: >=3.9.5
Classifier: License :: OSI Approved :: MIT License
Classifier: Programming Language :: Python :: 3
Classifier: Programming Language :: Python :: 3.10
Classifier: Programming Language :: Python :: 3.11
Classifier: Programming Language :: Python :: 3.12
Classifier: Programming Language :: Python :: 3.13
Requires-Dist: cryptography (>=45.0.2,<46.0.0)
Requires-Dist: google-genai (>=1.9.0,<2.0.0)
